[
    {
        "id": "2022-03-31T13:11:38.497Z",
        "email": "alma@alma.hu",
        "name": "offer_c",
        "text": "asdsad",
        "event": "e2"
    },
    {
        "id": "2022-03-31T13:14:47.922Z",
        "email": "imre.varga97@gmail.com",
        "name": "Varga Imre",
        "text": "Jaj de jó működik a komment szekcióm mennyit tököltem vele de végre ez is meg van",
        "event": "e2"
    },
    {
        "id": "2022-03-31T13:16:15.966Z",
        "email": "alma@alma.hu",
        "name": "Butháné Barbara",
        "text": "nah akkor elméletileg ez egyből meg fog jelenni ",
        "event": "e2"
    },
    {
        "id": "2022-03-31T13:18:39.119Z",
        "email": "karre@macska.hu",
        "name": "Kiss Géza",
        "text": "nah akkor ide is tolok már egy kommentet",
        "event": "e3"
    },
    {
        "id": "2022-03-31T13:24:53.847Z",
        "email": "alma@alma.hu",
        "name": "asdas",
        "text": "fsadasd",
        "event": "e3"
    }
]